pyrfc/__init__.py
pyrfc/_exception.py
pyrfc/pyrfc.cpython-38-darwin.so
pynwrfc-2.4.0.dist-info/METADATA
pynwrfc-2.4.0.dist-info/WHEEL
pynwrfc-2.4.0.dist-info/top_level.txt
pynwrfc-2.4.0.dist-info/RECORD
