Metadata-Version: 2.1
Name: pynwrfc
Version: 2.4.0
Summary: Python bindings for SAP NetWeaver RFC SDK
Home-page: https://github.com/SAP/pyrfc
Author: SAP SE
Maintainer: Srdjan Boskovic
Maintainer-email: srdjan.boskovic@sap.com
License: OSI Approved :: Apache Software License
Download-URL: https://github.com/SAP/PyRFC/tarball/master
Keywords: pyrfc pynwrfc pyrfc sap rfc nwrfc sapnwrfc
Platform: UNKNOWN
Classifier: Development Status :: 5 - Production/Stable
Classifier: Intended Audience :: Developers
Classifier: Natural Language :: English
Classifier: License :: OSI Approved :: Apache Software License
Classifier: Operating System :: OS Independent
Classifier: Programming Language :: Cython
Classifier: Programming Language :: Python
Classifier: Programming Language :: Python :: 3.6
Classifier: Programming Language :: Python :: 3.7
Classifier: Programming Language :: Python :: 3.8
Classifier: Programming Language :: Python :: 3.9
Requires-Dist: setuptools
